{
  "nhits": 2,
  "parameters": {
    "dataset": "real-time-bezettingen-fietsenstallingen-gent",
    "rows": 10,
    "start": 0,
    "facet": [
      "facilityname"
    ],
    "format": "json",
    "timezone": "Europe/Brussels"
  },
  "records": [
    {
      "datasetid": "real-time-bezettingen-fietsenstallingen-gent",
      "recordid": "bb2b76662319e21bd96eb5657cc39d854f0b8b53",
      "fields": {
        "id": "48-1",
        "freeplaces": 53,
        "facilityname": "Korenmarkt",
        "geo_point_2d": [
          51.05388288288933,
          3.7214177570400473
        ],
        "time": "2022-12-11T21:47:19+01:00",
        "totalplaces": 235,
        "occupiedplaces": 182,
        "bezetting": 77
      },
      "geometry": {
        "type": "Point",
        "coordinates": [
          3.7214177570400473,
          51.05388288288933
        ]
      },
      "record_timestamp": "2022-12-11T21:48:05.798+01:00"
    },
    {
      "datasetid": "real-time-bezettingen-fietsenstallingen-gent",
      "recordid": "3edfc123825b0e8efdd52ed6e1edc33853f6a968",
      "fields": {
        "id": "48-2",
        "freeplaces": 88,
        "facilityname": "Braunplein",
        "geo_point_2d": [
          51.05406845807926,
          3.723722319130363
        ],
        "time": "2022-12-11T21:47:19+01:00",
        "totalplaces": 116,
        "occupiedplaces": 28,
        "bezetting": 24
      },
      "geometry": {
        "type": "Point",
        "coordinates": [
          3.723722319130363,
          51.05406845807926
        ]
      },
      "record_timestamp": "2022-12-11T21:48:05.798+01:00"
    }
  ],
  "facet_groups": [
    {
      "name": "facilityname",
      "facets": [
        {
          "name": "Braunplein",
          "count": 1,
          "state": "displayed",
          "path": "Braunplein"
        },
        {
          "name": "Korenmarkt",
          "count": 1,
          "state": "displayed",
          "path": "Korenmarkt"
        }
      ]
    }
  ]
}
